{
    "dial_idx": "MUL0724.json",
    "domains": [
        "train",
        "accommodation"
    ],
    "goal_text": "You are looking for information in Cambridge.\nYou are looking for a 'train'. The train should depart from 'cambridge' and should 'leave after 10:00'.\nThe train should leave on 'sunday' and should go to 'birmingham new street'.\nOnce you find the train you want to make a booking for '1 people'.\nMake sure you get the 'reference number'.\nYou are also looking for a 'particular hotel'. Its name is called 'alexander bed and breakfast'.\nMake sure you get 'star of the hotel', 'hotel type', and 'price range'.Remember. You don't want booking for accomodation. Just get the information and it all done.\n",
    "goal_dict": {
        "taxi": {},
        "police": {},
        "hospital": {},
        "attraction": {},
        "train": {
            "info": {
                "leaveAt": "10:00",
                "destination": "birmingham new street",
                "day": "sunday",
                "departure": "cambridge"
            },
            "fail_info": {},
            "book": {
                "invalid": true,
                "people": "1"
            },
            "fail_book": {}
        },
        "message": [
            "You are looking for information in Cambridge",
            "You are looking for a <span class='emphasis'>train</span>. The train should depart from <span class='emphasis'>cambridge</span> and should <span class='emphasis'>leave after 10:00</span>",
            "The train should leave on <span class='emphasis'>sunday</span> and should go to <span class='emphasis'>birmingham new street</span>",
            "Once you find the train you want to make a booking for <span class='emphasis'>1 people</span>",
            "Make sure you get the <span class='emphasis'>reference number</span>",
            "You are also looking for a <span class='emphasis'>particular hotel</span>. Its name is called <span class='emphasis'>alexander bed and breakfast</span>",
            "Make sure you get <span class='emphasis'>star of the hotel</span>, <span class='emphasis'>hotel type</span>, and <span class='emphasis'>price range</span>"
        ],
        "restaurant": {},
        "accommodation": {
            "info": {
                "name": "alexander bed and breakfast"
            },
            "reqt": [
                "stars",
                "type",
                "pricerange"
            ],
            "fail_info": {
                "name": "leverton house"
            }
        }
    }
}