{
    "dial_idx": "MUL0181.json",
    "domains": [
        "restaurant",
        "accommodation"
    ],
    "goal_text": "You are looking for information in Cambridge.\nYou are looking for a place to stay. The hotel should be in the type of 'guesthouse' and should be in the 'east'.\nThe hotel should 'include free parking'.\nMake sure you get 'phone number' and 'postcode'.\nYou are also looking for a 'restaurant'. The restaurant should serve 'cuban' food and should be in the 'moderate' price range.\nIf there is no such restaurant, how about one that serves 'chinese' food.\nMake sure you get 'area' and 'postcode'.Remember. You don't want booking for restaurant. Just get the information and it all done.\nRemember. You don't want booking for accomodation. Just get the information and it all done.\n",
    "goal_dict": {
        "taxi": {},
        "police": {},
        "hospital": {},
        "attraction": {},
        "train": {},
        "message": [
            "You are looking for information in Cambridge",
            "You are looking for a <span class='emphasis'>place to stay</span>. The hotel should be in the type of <span class='emphasis'>guesthouse</span> and should be in the <span class='emphasis'>east</span>",
            "The hotel should <span class='emphasis'>include free parking</span>",
            "Make sure you get <span class='emphasis'>phone number</span> and <span class='emphasis'>postcode</span>",
            "You are also looking for a <span class='emphasis'>restaurant</span>. The restaurant should serve <span class='emphasis'>cuban</span> food and should be in the <span class='emphasis'>moderate</span> price range",
            "If there is no such restaurant, how about one that serves <span class='emphasis'>chinese</span> food",
            "Make sure you get <span class='emphasis'>area</span> and <span class='emphasis'>postcode</span>"
        ],
        "restaurant": {
            "info": {
                "food": "chinese",
                "pricerange": "moderate"
            },
            "reqt": [
                "area",
                "postcode"
            ],
            "fail_info": {
                "food": "cuban",
                "pricerange": "moderate"
            }
        },
        "accommodation": {
            "info": {
                "area": "east",
                "type": "guesthouse",
                "parking": "yes"
            },
            "reqt": [
                "phone",
                "postcode"
            ],
            "fail_info": {}
        }
    }
}