{
    "dial_idx": "MUL2049.json",
    "domains": [
        "train",
        "accommodation"
    ],
    "goal_text": "You are looking for information in Cambridge.\nYou are looking for a place to stay. The hotel should be in the 'moderate' price range and should be in the 'north'.\nThe hotel should be in the type of 'guesthouse' and should 'include free parking'.\nOnce you find the 'hotel' you want to book it for '3 people' and '3 nights' starting from 'wednesday'.\nMake sure you get the 'reference number'.\nYou are also looking for a 'train'. The train should depart from 'bishops stortford' and should go to 'cambridge'.\nThe train should be on 'the same day as the hotel booking' and should 'leave after 16:45'.\nOnce you find the train you want to make a booking for 'the same group of people'.\nMake sure you get the 'reference number'.",
    "goal_dict": {
        "taxi": {},
        "police": {},
        "hospital": {},
        "attraction": {},
        "train": {
            "info": {
                "leaveAt": "16:45",
                "destination": "cambridge",
                "day": "wednesday",
                "departure": "bishops stortford"
            },
            "fail_info": {},
            "book": {
                "invalid": false,
                "people": "3"
            },
            "fail_book": {}
        },
        "message": [
            "You are looking for information in Cambridge",
            "You are looking for a <span class='emphasis'>place to stay</span>. The hotel should be in the <span class='emphasis'>moderate</span> price range and should be in the <span class='emphasis'>north</span>",
            "The hotel should be in the type of <span class='emphasis'>guesthouse</span> and should <span class='emphasis'>include free parking</span>",
            "Once you find the <span class='emphasis'>hotel</span> you want to book it for <span class='emphasis'>3 people</span> and <span class='emphasis'>3 nights</span> starting from <span class='emphasis'>wednesday</span>",
            "Make sure you get the <span class='emphasis'>reference number</span>",
            "You are also looking for a <span class='emphasis'>train</span>. The train should depart from <span class='emphasis'>bishops stortford</span> and should go to <span class='emphasis'>cambridge</span>",
            "The train should be on <span class='emphasis'>the same day as the hotel booking</span> and should <span class='emphasis'>leave after 16:45</span>",
            "Once you find the train you want to make a booking for <span class='emphasis'>the same group of people</span>",
            "Make sure you get the <span class='emphasis'>reference number</span>"
        ],
        "restaurant": {},
        "accommodation": {
            "info": {
                "type": "guesthouse",
                "parking": "yes",
                "pricerange": "moderate",
                "area": "north"
            },
            "fail_info": {},
            "book": {
                "stay": "3",
                "day": "wednesday",
                "invalid": false,
                "people": "3"
            },
            "fail_book": {}
        }
    }
}