{
    "dial_idx": "MUL2446.json",
    "domains": [
        "attraction",
        "restaurant"
    ],
    "goal_text": "You are traveling to Cambridge and excited about seeing local tourist attractions.\nYou are looking for places to go in town. The attraction should be in the type of 'college'.\nMake sure you get 'phone number', 'entrance fee', and 'address'.\nYou are also looking for a place to dine. The restaurant should serve 'italian' food and should be in the 'cheap' price range.\nMake sure you get 'area'.Remember. You don't want booking for restaurant. Just get the information and it all done.\n",
    "goal_dict": {
        "taxi": {},
        "police": {},
        "hospital": {},
        "attraction": {
            "info": {
                "type": "college"
            },
            "reqt": [
                "phone",
                "entrance fee",
                "address"
            ],
            "fail_info": {}
        },
        "train": {},
        "message": [
            "You are traveling to Cambridge and excited about seeing local tourist attractions",
            "You are looking for <span class='emphasis'>places to go</span> in town. The attraction should be in the type of <span class='emphasis'>college</span>",
            "Make sure you get <span class='emphasis'>phone number</span>, <span class='emphasis'>entrance fee</span>, and <span class='emphasis'>address</span>",
            "You are also looking for a <span class='emphasis'>place to dine</span>. The restaurant should serve <span class='emphasis'>italian</span> food and should be in the <span class='emphasis'>cheap</span> price range",
            "Make sure you get <span class='emphasis'>area</span>"
        ],
        "restaurant": {
            "info": {
                "food": "italian",
                "pricerange": "cheap"
            },
            "reqt": [
                "area"
            ],
            "fail_info": {}
        },
        "accommodation": {}
    }
}