{
    "dial_idx": "MUL2620.json",
    "domains": [
        "taxi",
        "attraction",
        "accommodation"
    ],
    "goal_text": "You are looking for information in Cambridge.\nYou are looking for a 'particular hotel'. Its name is called 'el shaddai'.\nOnce you find the 'hotel' you want to book it for '1 people' and '5 nights' starting from 'wednesday'.\nIf the booking fails how about '3 nights'.\nMake sure you get the 'reference number'.\nYou are also looking for places to go in town. The attraction should be in the type of 'swimmingpool' and should be in the 'north'.\nMake sure you get 'phone number'.\nYou also want to book a 'taxi' to commute between the two places.\nYou want to leave the 'hotel' by '04:30'.\nMake sure you get 'contact number' and 'car type'.",
    "goal_dict": {
        "taxi": {
            "reqt": [
                "car type",
                "phone"
            ],
            "fail_info": {},
            "book": {
                "leaveAt": "04:30"
            }
        },
        "police": {},
        "hospital": {},
        "attraction": {
            "info": {
                "type": "swimmingpool",
                "area": "north"
            },
            "reqt": [
                "phone"
            ],
            "fail_info": {}
        },
        "train": {},
        "message": [
            "You are looking for information in Cambridge",
            "You are looking for a <span class='emphasis'>particular hotel</span>. Its name is called <span class='emphasis'>el shaddai</span>",
            "Once you find the <span class='emphasis'>hotel</span> you want to book it for <span class='emphasis'>1 people</span> and <span class='emphasis'>5 nights</span> starting from <span class='emphasis'>wednesday</span>",
            "If the booking fails how about <span class='emphasis'>3 nights</span>",
            "Make sure you get the <span class='emphasis'>reference number</span>",
            "You are also looking for <span class='emphasis'>places to go</span> in town. The attraction should be in the type of <span class='emphasis'>swimmingpool</span> and should be in the <span class='emphasis'>north</span>",
            "Make sure you get <span class='emphasis'>phone number</span>",
            "You also want to book a <span class='emphasis'>taxi</span> to commute between the two places",
            "You want to leave the <span class='emphasis'>hotel</span> by <span class='emphasis'>04:30</span>",
            "Make sure you get <span class='emphasis'>contact number</span> and <span class='emphasis'>car type</span>"
        ],
        "restaurant": {},
        "accommodation": {
            "info": {
                "name": "el shaddai"
            },
            "fail_info": {},
            "book": {
                "pre_invalid": true,
                "stay": "3",
                "day": "wednesday",
                "invalid": false,
                "people": "1"
            },
            "fail_book": {
                "stay": "5"
            }
        }
    }
}