{
    "dial_idx": "MUL2002.json",
    "domains": [
        "train",
        "accommodation"
    ],
    "goal_text": "You are planning your trip in Cambridge.\nYou are looking for a 'train'. The train should leave on 'friday' and should depart from 'london liverpool street'.\nThe train should go to 'cambridge' and should 'arrive by 15:15'.\nMake sure you get 'train ID', 'travel time', and 'departure time'.\nYou are also looking for a place to stay. The hotel should 'include free parking' and should be in the type of 'guesthouse'.\nThe hotel should be in the 'cheap' price range.\nMake sure you get 'address' and 'area'.Remember. You don't want booking for train. Just get the information and it all done.\nRemember. You don't want booking for accomodation. Just get the information and it all done.\n",
    "goal_dict": {
        "taxi": {},
        "police": {},
        "hospital": {},
        "attraction": {},
        "train": {
            "info": {
                "destination": "cambridge",
                "day": "friday",
                "arriveBy": "15:15",
                "departure": "london liverpool street"
            },
            "reqt": [
                "trainID",
                "duration",
                "leaveAt"
            ],
            "fail_info": {}
        },
        "message": [
            "You are planning your trip in Cambridge",
            "You are looking for a <span class='emphasis'>train</span>. The train should leave on <span class='emphasis'>friday</span> and should depart from <span class='emphasis'>london liverpool street</span>",
            "The train should go to <span class='emphasis'>cambridge</span> and should <span class='emphasis'>arrive by 15:15</span>",
            "Make sure you get <span class='emphasis'>train ID</span>, <span class='emphasis'>travel time</span>, and <span class='emphasis'>departure time</span>",
            "You are also looking for a <span class='emphasis'>place to stay</span>. The hotel should <span class='emphasis'>include free parking</span> and should be in the type of <span class='emphasis'>guesthouse</span>",
            "The hotel should be in the <span class='emphasis'>cheap</span> price range",
            "Make sure you get <span class='emphasis'>address</span> and <span class='emphasis'>area</span>"
        ],
        "restaurant": {},
        "accommodation": {
            "info": {
                "type": "guesthouse",
                "pricerange": "cheap",
                "parking": "yes"
            },
            "reqt": [
                "address",
                "area"
            ],
            "fail_info": {}
        }
    }
}