{
    "dial_idx": "MUL2435.json",
    "domains": [
        "attraction",
        "restaurant"
    ],
    "goal_text": "You are traveling to Cambridge and looking forward to try local restaurants.\nYou are looking for a 'particular attraction'. Its name is called 'cambridge book and print gallery'.\nMake sure you get 'phone number' and 'area'.\nYou are also looking for a 'restaurant'. The restaurant should be in the 'centre' and should be in the 'moderate' price range.\nThe restaurant should serve 'british' food.\nMake sure you get 'phone number'.Remember. You don't want booking for restaurant. Just get the information and it all done.\n",
    "goal_dict": {
        "taxi": {},
        "police": {},
        "hospital": {},
        "attraction": {
            "info": {
                "name": "cambridge book and print gallery"
            },
            "reqt": [
                "phone",
                "area"
            ],
            "fail_info": {
                "name": "the fez club"
            }
        },
        "train": {},
        "message": [
            "You are traveling to Cambridge and looking forward to try local restaurants",
            "You are looking for a <span class='emphasis'>particular attraction</span>. Its name is called <span class='emphasis'>cambridge book and print gallery</span>",
            "Make sure you get <span class='emphasis'>phone number</span> and <span class='emphasis'>area</span>",
            "You are also looking for a <span class='emphasis'>restaurant</span>. The restaurant should be in the <span class='emphasis'>centre</span> and should be in the <span class='emphasis'>moderate</span> price range",
            "The restaurant should serve <span class='emphasis'>british</span> food",
            "Make sure you get <span class='emphasis'>phone number</span>"
        ],
        "restaurant": {
            "info": {
                "food": "british",
                "pricerange": "moderate",
                "area": "centre"
            },
            "reqt": [
                "phone"
            ],
            "fail_info": {}
        },
        "accommodation": {}
    }
}