{
    "dial_idx": "MUL2481.json",
    "domains": [
        "attraction",
        "restaurant"
    ],
    "goal_text": "You are traveling to Cambridge and excited about seeing local tourist attractions.\nYou are looking for a place to dine. The restaurant should be in the 'moderate' price range and should serve 'indian' food.\nThe restaurant should be in the 'west'.\nMake sure you get 'postcode' and 'address'.\nYou are also looking for places to go in town. The attraction should be in the type of 'boat'.\nMake sure you get 'entrance fee' and 'postcode'.Remember. You don't want booking for restaurant. Just get the information and it all done.\n",
    "goal_dict": {
        "taxi": {},
        "police": {},
        "hospital": {},
        "attraction": {
            "info": {
                "type": "boat"
            },
            "reqt": [
                "entrance fee",
                "postcode"
            ],
            "fail_info": {
                "type": "architecture"
            }
        },
        "train": {},
        "message": [
            "You are traveling to Cambridge and excited about seeing local tourist attractions",
            "You are looking for a <span class='emphasis'>place to dine</span>. The restaurant should be in the <span class='emphasis'>moderate</span> price range and should serve <span class='emphasis'>indian</span> food",
            "The restaurant should be in the <span class='emphasis'>west</span>",
            "Make sure you get <span class='emphasis'>postcode</span> and <span class='emphasis'>address</span>",
            "You are also looking for <span class='emphasis'>places to go</span> in town. The attraction should be in the type of <span class='emphasis'>boat</span>",
            "Make sure you get <span class='emphasis'>entrance fee</span> and <span class='emphasis'>postcode</span>"
        ],
        "restaurant": {
            "info": {
                "food": "indian",
                "pricerange": "moderate",
                "area": "west"
            },
            "reqt": [
                "postcode",
                "address"
            ],
            "fail_info": {}
        },
        "accommodation": {}
    }
}