{
    "dial_idx": "MUL2114.json",
    "domains": [
        "train",
        "accommodation"
    ],
    "goal_text": "You are looking for information in Cambridge.\nYou are looking for a 'train'. The train should leave on 'friday' and should 'leave after 11:45'.\nThe train should depart from 'london kings cross' and should go to 'cambridge'.\nMake sure you get 'train ID', 'price', and 'travel time'.\nYou are also looking for a place to stay. The hotel should 'include free wifi' and should 'include free parking'.\nThe hotel should be in the 'south'.\nMake sure you get 'hotel type'.Remember. You don't want booking for train. Just get the information and it all done.\nRemember. You don't want booking for accomodation. Just get the information and it all done.\n",
    "goal_dict": {
        "taxi": {},
        "police": {},
        "hospital": {},
        "attraction": {},
        "train": {
            "info": {
                "leaveAt": "11:45",
                "destination": "cambridge",
                "day": "friday",
                "departure": "london kings cross"
            },
            "reqt": [
                "trainID",
                "price",
                "duration"
            ],
            "fail_info": {}
        },
        "message": [
            "You are looking for information in Cambridge",
            "You are looking for a <span class='emphasis'>train</span>. The train should leave on <span class='emphasis'>friday</span> and should <span class='emphasis'>leave after 11:45</span>",
            "The train should depart from <span class='emphasis'>london kings cross</span> and should go to <span class='emphasis'>cambridge</span>",
            "Make sure you get <span class='emphasis'>train ID</span>, <span class='emphasis'>price</span>, and <span class='emphasis'>travel time</span>",
            "You are also looking for a <span class='emphasis'>place to stay</span>. The hotel should <span class='emphasis'>include free wifi</span> and should <span class='emphasis'>include free parking</span>",
            "The hotel should be in the <span class='emphasis'>south</span>",
            "Make sure you get <span class='emphasis'>hotel type</span>"
        ],
        "restaurant": {},
        "accommodation": {
            "info": {
                "area": "south",
                "internet": "yes",
                "parking": "yes"
            },
            "reqt": [
                "type"
            ],
            "fail_info": {}
        }
    }
}