{
    "dial_idx": "PMUL4977.json",
    "domains": [
        "train",
        "accommodation"
    ],
    "goal_text": "You are planning your trip in Cambridge.\nYou are looking for a 'train'. The train should go to 'cambridge' and should leave on 'saturday'.\nThe train should 'leave after 15:30' and should depart from 'ely'.\nMake sure you get 'train ID'.\nYou are also looking for a place to stay. The hotel should be in the type of 'hotel' and should have 'a star of 2'.\nThe hotel should be in the 'north' and should be in the 'moderate' price range.\nOnce you find the 'hotel' you want to book it for '8 people' and '5 nights' starting from 'the same day'.\nMake sure you get the 'reference number'.Remember. You don't want booking for train. Just get the information and it all done.\n",
    "goal_dict": {
        "taxi": {},
        "police": {},
        "hospital": {},
        "topic": {
            "taxi": false,
            "police": false,
            "restaurant": false,
            "hospital": false,
            "hotel": false,
            "general": false,
            "attraction": false,
            "train": false,
            "booking": false
        },
        "attraction": {},
        "train": {
            "info": {
                "leaveAt": "15:30",
                "destination": "cambridge",
                "day": "saturday",
                "departure": "ely"
            },
            "reqt": [
                "trainID"
            ],
            "fail_info": {}
        },
        "message": [
            "You are planning your trip in Cambridge",
            "You are looking for a <span class='emphasis'>train</span>. The train should go to <span class='emphasis'>cambridge</span> and should leave on <span class='emphasis'>saturday</span>",
            "The train should <span class='emphasis'>leave after 15:30</span> and should depart from <span class='emphasis'>ely</span>",
            "Make sure you get <span class='emphasis'>train ID</span>",
            "You are also looking for a <span class='emphasis'>place to stay</span>. The hotel should be in the type of <span class='emphasis'>hotel</span> and should have <span class='emphasis'>a star of 2</span>",
            "The hotel should be in the <span class='emphasis'>north</span> and should be in the <span class='emphasis'>moderate</span> price range",
            "Once you find the <span class='emphasis'>hotel</span> you want to book it for <span class='emphasis'>8 people</span> and <span class='emphasis'>5 nights</span> starting from <span class='emphasis'>the same day</span>",
            "Make sure you get the <span class='emphasis'>reference number</span>"
        ],
        "restaurant": {},
        "accommodation": {
            "info": {
                "pricerange": "moderate",
                "type": "hotel",
                "stars": "2",
                "area": "north"
            },
            "fail_info": {},
            "book": {
                "people": "8",
                "day": "saturday",
                "invalid": false,
                "stay": "5"
            },
            "fail_book": {}
        }
    }
}