{
    "dial_idx": "PMUL1783.json",
    "domains": [
        "train",
        "accommodation"
    ],
    "goal_text": "You are looking for information in Cambridge.\nYou are looking for a place to stay. The hotel should be in the 'west' and should be in the 'expensive' price range.\nThe hotel should 'include free wifi'.\nOnce you find the 'hotel' you want to book it for '4 people' and '5 nights' starting from 'saturday'.\nMake sure you get the 'reference number'.\nYou are also looking for a 'train'. The train should leave on 'thursday' and should 'leave after 16:45'.\nThe train should go to 'london kings cross' and should depart from 'cambridge'.\nOnce you find the train you want to make a booking for 'the same group of people'.\nMake sure you get the 'reference number'.",
    "goal_dict": {
        "taxi": {},
        "police": {},
        "hospital": {},
        "topic": {
            "taxi": false,
            "police": false,
            "restaurant": false,
            "hospital": false,
            "hotel": false,
            "general": false,
            "attraction": false,
            "train": false,
            "booking": false
        },
        "attraction": {},
        "train": {
            "info": {
                "leaveAt": "16:45",
                "destination": "london kings cross",
                "day": "thursday",
                "departure": "cambridge"
            },
            "fail_info": {},
            "book": {
                "invalid": false,
                "people": "4"
            },
            "fail_book": {}
        },
        "message": [
            "You are looking for information in Cambridge",
            "You are looking for a <span class='emphasis'>place to stay</span>. The hotel should be in the <span class='emphasis'>west</span> and should be in the <span class='emphasis'>expensive</span> price range",
            "The hotel should <span class='emphasis'>include free wifi</span>",
            "Once you find the <span class='emphasis'>hotel</span> you want to book it for <span class='emphasis'>4 people</span> and <span class='emphasis'>5 nights</span> starting from <span class='emphasis'>saturday</span>",
            "Make sure you get the <span class='emphasis'>reference number</span>",
            "You are also looking for a <span class='emphasis'>train</span>. The train should leave on <span class='emphasis'>thursday</span> and should <span class='emphasis'>leave after 16:45</span>",
            "The train should go to <span class='emphasis'>london kings cross</span> and should depart from <span class='emphasis'>cambridge</span>",
            "Once you find the train you want to make a booking for <span class='emphasis'>the same group of people</span>",
            "Make sure you get the <span class='emphasis'>reference number</span>"
        ],
        "restaurant": {},
        "accommodation": {
            "info": {
                "area": "west",
                "pricerange": "expensive",
                "internet": "yes"
            },
            "fail_info": {},
            "book": {
                "people": "4",
                "day": "saturday",
                "invalid": false,
                "stay": "5"
            },
            "fail_book": {}
        }
    }
}