{
    "dial_idx": "PMUL4202.json",
    "domains": [
        "taxi",
        "attraction",
        "restaurant"
    ],
    "goal_text": "You are traveling to Cambridge and excited about seeing local tourist attractions.\nYou are looking for a place to dine. The restaurant should serve 'indian' food and should be in the 'cheap' price range.\nThe restaurant should be in the 'centre'.\nOnce you find the 'restaurant' you want to book a table for '5 people' at '12:15' on 'saturday'.\nMake sure you get the 'reference number'.\nYou are also looking for a 'particular attraction'. Its name is called 'vue cinema'.\nMake sure you get 'attraction type' and 'postcode'.\nYou also want to book a 'taxi' to commute between the two places.\nYou want to make sure it arrives the restaurant 'by the booked time'.\nMake sure you get 'contact number' and 'car type'.",
    "goal_dict": {
        "taxi": {
            "reqt": [
                "car type",
                "phone"
            ],
            "fail_info": {},
            "book": {
                "arriveBy": "12:15"
            }
        },
        "police": {},
        "hospital": {},
        "topic": {
            "taxi": false,
            "police": false,
            "restaurant": false,
            "hospital": false,
            "hotel": false,
            "general": false,
            "attraction": false,
            "train": false,
            "booking": false
        },
        "attraction": {
            "info": {
                "name": "vue cinema"
            },
            "reqt": [
                "type",
                "postcode"
            ],
            "fail_info": {
                "name": "the junction"
            }
        },
        "train": {},
        "message": [
            "You are traveling to Cambridge and excited about seeing local tourist attractions",
            "You are looking for a <span class='emphasis'>place to dine</span>. The restaurant should serve <span class='emphasis'>indian</span> food and should be in the <span class='emphasis'>cheap</span> price range",
            "The restaurant should be in the <span class='emphasis'>centre</span>",
            "Once you find the <span class='emphasis'>restaurant</span> you want to book a table for <span class='emphasis'>5 people</span> at <span class='emphasis'>12:15</span> on <span class='emphasis'>saturday</span>",
            "Make sure you get the <span class='emphasis'>reference number</span>",
            "You are also looking for a <span class='emphasis'>particular attraction</span>. Its name is called <span class='emphasis'>vue cinema</span>",
            "Make sure you get <span class='emphasis'>attraction type</span> and <span class='emphasis'>postcode</span>",
            "You also want to book a <span class='emphasis'>taxi</span> to commute between the two places",
            "You want to make sure it arrives the restaurant <span class='emphasis'>by the booked time</span>",
            "Make sure you get <span class='emphasis'>contact number</span> and <span class='emphasis'>car type</span>"
        ],
        "restaurant": {
            "info": {
                "food": "indian",
                "pricerange": "cheap",
                "area": "centre"
            },
            "fail_info": {},
            "book": {
                "people": "5",
                "day": "saturday",
                "invalid": false,
                "time": "12:15"
            },
            "fail_book": {}
        },
        "accommodation": {}
    }
}