{
    "dial_idx": "PMUL3125.json",
    "domains": [
        "restaurant",
        "train"
    ],
    "goal_text": "You are looking for information in Cambridge.\nYou are looking for a 'restaurant'. The restaurant should be in the 'moderate' price range and should serve 'british' food.\nThe restaurant should be in the 'centre'.\nMake sure you get 'phone number'.\nYou are also looking for a 'train'. The train should 'arrive by 11:30' and should depart from 'ely'.\nThe train should leave on 'tuesday' and should go to 'cambridge'.\nOnce you find the train you want to make a booking for '8 people'.\nMake sure you get the 'reference number'.Remember. You don't want booking for restaurant. Just get the information and it all done.\n",
    "goal_dict": {
        "taxi": {},
        "police": {},
        "hospital": {},
        "topic": {
            "taxi": false,
            "police": false,
            "restaurant": false,
            "hospital": false,
            "hotel": false,
            "general": false,
            "attraction": false,
            "train": false,
            "booking": false
        },
        "attraction": {},
        "train": {
            "info": {
                "destination": "cambridge",
                "day": "tuesday",
                "arriveBy": "11:30",
                "departure": "ely"
            },
            "fail_info": {},
            "book": {
                "invalid": true,
                "people": "8"
            },
            "fail_book": {}
        },
        "message": [
            "You are looking for information in Cambridge",
            "You are looking for a <span class='emphasis'>restaurant</span>. The restaurant should be in the <span class='emphasis'>moderate</span> price range and should serve <span class='emphasis'>british</span> food",
            "The restaurant should be in the <span class='emphasis'>centre</span>",
            "Make sure you get <span class='emphasis'>phone number</span>",
            "You are also looking for a <span class='emphasis'>train</span>. The train should <span class='emphasis'>arrive by 11:30</span> and should depart from <span class='emphasis'>ely</span>",
            "The train should leave on <span class='emphasis'>tuesday</span> and should go to <span class='emphasis'>cambridge</span>",
            "Once you find the train you want to make a booking for <span class='emphasis'>8 people</span>",
            "Make sure you get the <span class='emphasis'>reference number</span>"
        ],
        "restaurant": {
            "info": {
                "food": "british",
                "pricerange": "moderate",
                "area": "centre"
            },
            "reqt": [
                "phone"
            ],
            "fail_info": {}
        },
        "accommodation": {}
    }
}