{
    "dial_idx": "PMUL4664.json",
    "domains": [
        "restaurant",
        "train"
    ],
    "goal_text": "You are planning your trip in Cambridge.\nYou are looking for a 'train'. The train should leave on 'thursday' and should 'arrive by 18:30'.\nThe train should depart from 'cambridge' and should go to 'stansted airport'.\nMake sure you get 'train ID' and 'travel time'.\nYou are also looking for a 'particular restaurant'. Its name is called 'nandos city centre'.\nMake sure you get 'postcode'.Remember. You don't want booking for restaurant. Just get the information and it all done.\nRemember. You don't want booking for train. Just get the information and it all done.\n",
    "goal_dict": {
        "taxi": {},
        "police": {},
        "hospital": {},
        "topic": {
            "taxi": false,
            "police": false,
            "restaurant": false,
            "hospital": false,
            "hotel": false,
            "general": false,
            "attraction": false,
            "train": false,
            "booking": false
        },
        "attraction": {},
        "train": {
            "info": {
                "destination": "stansted airport",
                "day": "thursday",
                "arriveBy": "18:30",
                "departure": "cambridge"
            },
            "reqt": [
                "trainID",
                "duration"
            ],
            "fail_info": {}
        },
        "message": [
            "You are planning your trip in Cambridge",
            "You are looking for a <span class='emphasis'>train</span>. The train should leave on <span class='emphasis'>thursday</span> and should <span class='emphasis'>arrive by 18:30</span>",
            "The train should depart from <span class='emphasis'>cambridge</span> and should go to <span class='emphasis'>stansted airport</span>",
            "Make sure you get <span class='emphasis'>train ID</span> and <span class='emphasis'>travel time</span>",
            "You are also looking for a <span class='emphasis'>particular restaurant</span>. Its name is called <span class='emphasis'>nandos city centre</span>",
            "Make sure you get <span class='emphasis'>postcode</span>"
        ],
        "restaurant": {
            "info": {
                "name": "nandos city centre"
            },
            "reqt": [
                "postcode"
            ],
            "fail_info": {
                "name": "caffe uno"
            }
        },
        "accommodation": {}
    }
}