{
    "dial_idx": "PMUL3038.json",
    "domains": [
        "restaurant",
        "accommodation"
    ],
    "goal_text": "You are looking for information in Cambridge.\nYou are looking for a place to stay. The hotel should 'include free wifi' and should 'include free parking'.\nThe hotel should be in the 'cheap' price range and should have 'a star of 0'.\nMake sure you get 'hotel type', 'area', and 'postcode'.\nYou are also looking for a 'particular restaurant'. Its name is called 'graffiti'.\nMake sure you get 'food type' and 'area'.Remember. You don't want booking for restaurant. Just get the information and it all done.\nRemember. You don't want booking for accomodation. Just get the information and it all done.\n",
    "goal_dict": {
        "taxi": {},
        "police": {},
        "hospital": {},
        "topic": {
            "taxi": false,
            "police": false,
            "restaurant": false,
            "hospital": false,
            "hotel": false,
            "general": false,
            "attraction": false,
            "train": false,
            "booking": false
        },
        "attraction": {},
        "train": {},
        "message": [
            "You are looking for information in Cambridge",
            "You are looking for a <span class='emphasis'>place to stay</span>. The hotel should <span class='emphasis'>include free wifi</span> and should <span class='emphasis'>include free parking</span>",
            "The hotel should be in the <span class='emphasis'>cheap</span> price range and should have <span class='emphasis'>a star of 0</span>",
            "Make sure you get <span class='emphasis'>hotel type</span>, <span class='emphasis'>area</span>, and <span class='emphasis'>postcode</span>",
            "You are also looking for a <span class='emphasis'>particular restaurant</span>. Its name is called <span class='emphasis'>graffiti</span>",
            "Make sure you get <span class='emphasis'>food type</span> and <span class='emphasis'>area</span>"
        ],
        "restaurant": {
            "info": {
                "name": "graffiti"
            },
            "reqt": [
                "food",
                "area"
            ],
            "fail_info": {
                "name": "thanh binh"
            }
        },
        "accommodation": {
            "info": {
                "internet": "yes",
                "pricerange": "cheap",
                "stars": "0",
                "parking": "yes"
            },
            "reqt": [
                "type",
                "area",
                "postcode"
            ],
            "fail_info": {}
        }
    }
}