{
    "dial_idx": "SNG0957.json",
    "domains": [
        "accommodation"
    ],
    "goal_text": "You are looking for a 'particular hotel'. Its name is called 'avalon'.\nMake sure you get 'price range' and 'phone number'.Remember. You don't want booking for accomodation. Just get the information and it all done.\n",
    "goal_dict": {
        "taxi": {},
        "police": {},
        "hospital": {},
        "attraction": {},
        "train": {},
        "message": [
            "You are looking for a <span class='emphasis'>particular hotel</span>. Its name is called <span class='emphasis'>avalon</span>",
            "Make sure you get <span class='emphasis'>price range</span> and <span class='emphasis'>phone number</span>"
        ],
        "restaurant": {},
        "accommodation": {
            "info": {
                "name": "avalon"
            },
            "reqt": [
                "pricerange",
                "phone"
            ],
            "fail_info": {
                "name": "avalon"
            }
        }
    }
}