{
    "dial_idx": "SNG0464.json",
    "domains": [
        "restaurant"
    ],
    "goal_text": "You are looking for a 'restaurant'. The restaurant should be in the 'cheap' price range and should serve 'creative' food.\nThe restaurant should be in the 'north'.\nIf there is no such restaurant, how about one that serves 'indian' food.\nMake sure you get 'postcode', 'phone number', and 'address'.Remember. You don't want booking for restaurant. Just get the information and it all done.\n",
    "goal_dict": {
        "taxi": {},
        "police": {},
        "hospital": {},
        "attraction": {},
        "train": {},
        "message": [
            "You are looking for a <span class='emphasis'>restaurant</span>. The restaurant should be in the <span class='emphasis'>cheap</span> price range and should serve <span class='emphasis'>creative</span> food",
            "The restaurant should be in the <span class='emphasis'>north</span>",
            "If there is no such restaurant, how about one that serves <span class='emphasis'>indian</span> food",
            "Make sure you get <span class='emphasis'>postcode</span>, <span class='emphasis'>phone number</span>, and <span class='emphasis'>address</span>"
        ],
        "restaurant": {
            "info": {
                "food": "indian",
                "pricerange": "cheap",
                "area": "north"
            },
            "reqt": [
                "postcode",
                "phone",
                "address"
            ],
            "fail_info": {
                "food": "creative",
                "pricerange": "cheap",
                "area": "north"
            }
        },
        "accommodation": {}
    }
}