{
    "dial_idx": "SNG01832.json",
    "domains": [
        "accommodation"
    ],
    "goal_text": "You are looking for a place to stay. The hotel should be in the type of 'guesthouse' and 'doesn't need to include internet'.\nThe hotel should be in the 'south'.\nIf there is no such hotel, how about one that has 'free wifi'.\nOnce you find the 'hotel' you want to book it for '6 people' and '2 nights' starting from 'tuesday'.\nMake sure you get the 'reference number'.",
    "goal_dict": {
        "taxi": {},
        "police": {},
        "hospital": {},
        "topic": {
            "taxi": false,
            "police": false,
            "restaurant": false,
            "hospital": false,
            "hotel": false,
            "general": false,
            "attraction": false,
            "train": false,
            "booking": false
        },
        "attraction": {},
        "train": {},
        "message": [
            "You are looking for a <span class='emphasis'>place to stay</span>. The hotel should be in the type of <span class='emphasis'>guesthouse</span> and <span class='emphasis'>doesn't need to include internet</span>",
            "The hotel should be in the <span class='emphasis'>south</span>",
            "If there is no such hotel, how about one that has <span class='emphasis'>free wifi</span>",
            "Once you find the <span class='emphasis'>hotel</span> you want to book it for <span class='emphasis'>6 people</span> and <span class='emphasis'>2 nights</span> starting from <span class='emphasis'>tuesday</span>",
            "Make sure you get the <span class='emphasis'>reference number</span>"
        ],
        "restaurant": {},
        "accommodation": {
            "info": {
                "internet": "yes",
                "type": "guesthouse",
                "area": "north"
            },
            "fail_info": {
                "internet": "no",
                "type": "guesthouse",
                "area": "south"
            },
            "book": {
                "stay": "2",
                "day": "tuesday",
                "invalid": false,
                "people": "6"
            },
            "fail_book": {}
        }
    }
}