{
    "dial_idx": "SNG0264.json",
    "domains": [
        "train"
    ],
    "goal_text": "You are looking for a 'train'. The train should leave on 'saturday' and should 'leave after 08:00'.\nThe train should depart from 'cambridge' and should go to 'kings lynn'.\nMake sure you get 'travel time' and 'train ID'.Remember. You don't want booking for train. Just get the information and it all done.\n",
    "goal_dict": {
        "taxi": {},
        "police": {},
        "hospital": {},
        "attraction": {},
        "train": {
            "info": {
                "leaveAt": "08:00",
                "destination": "kings lynn",
                "day": "saturday",
                "departure": "cambridge"
            },
            "reqt": [
                "duration",
                "trainID"
            ],
            "fail_info": {}
        },
        "message": [
            "You are looking for a <span class='emphasis'>train</span>. The train should leave on <span class='emphasis'>saturday</span> and should <span class='emphasis'>leave after 08:00</span>",
            "The train should depart from <span class='emphasis'>cambridge</span> and should go to <span class='emphasis'>kings lynn</span>",
            "Make sure you get <span class='emphasis'>travel time</span> and <span class='emphasis'>train ID</span>"
        ],
        "restaurant": {},
        "accommodation": {}
    }
}