{
    "dial_idx": "SNG02304.json",
    "domains": [
        "taxi"
    ],
    "goal_text": "You want to book a 'taxi'. The taxi should 'arrive by 23:30' and should depart from 'wandlebury country park'.\nThe taxi should go to 'tandoori palace'.\nMake sure you get 'car type' and 'contact number'.",
    "goal_dict": {
        "taxi": {
            "reqt": [
                "car type",
                "phone"
            ],
            "fail_info": {},
            "book": {
                "destination": "tandoori palace",
                "departure": "wandlebury country park",
                "arriveBy": "23:30"
            }
        },
        "police": {},
        "hospital": {},
        "topic": {
            "taxi": false,
            "police": false,
            "restaurant": false,
            "hospital": false,
            "hotel": false,
            "general": false,
            "attraction": false,
            "train": false,
            "booking": false
        },
        "attraction": {},
        "train": {},
        "message": [
            "You want to book a <span class='emphasis'>taxi</span>. The taxi should <span class='emphasis'>arrive by 23:30</span> and should depart from <span class='emphasis'>wandlebury country park</span>",
            "The taxi should go to <span class='emphasis'>tandoori palace</span>",
            "Make sure you get <span class='emphasis'>car type</span> and <span class='emphasis'>contact number</span>"
        ],
        "restaurant": {},
        "accommodation": {}
    }
}