{
    "dial_idx": "SNG01763.json",
    "domains": [
        "taxi"
    ],
    "goal_text": "You want to book a 'taxi'. The taxi should depart from 'leverton house' and should go to 'ugly duckling'.\nThe taxi should 'arrive by 23:30'.\nMake sure you get 'car type' and 'contact number'.",
    "goal_dict": {
        "taxi": {
            "reqt": [
                "car type",
                "phone"
            ],
            "fail_info": {},
            "book": {
                "destination": "ugly duckling",
                "departure": "leverton house",
                "arriveBy": "23:30"
            }
        },
        "police": {},
        "hospital": {},
        "topic": {
            "taxi": false,
            "police": false,
            "restaurant": false,
            "hospital": false,
            "hotel": false,
            "general": false,
            "attraction": false,
            "train": false,
            "booking": false
        },
        "attraction": {},
        "train": {},
        "message": [
            "You want to book a <span class='emphasis'>taxi</span>. The taxi should depart from <span class='emphasis'>leverton house</span> and should go to <span class='emphasis'>ugly duckling</span>",
            "The taxi should <span class='emphasis'>arrive by 23:30</span>",
            "Make sure you get <span class='emphasis'>car type</span> and <span class='emphasis'>contact number</span>"
        ],
        "restaurant": {},
        "accommodation": {}
    }
}