{
    "dial_idx": "WOZ20383.json",
    "domains": [
        "restaurant"
    ],
    "goal_text": "Task 06075: You want to find an expensive restaurant and it should be in the east part of town. You want to know the phone number and address of the venue.Remember. You don't want booking for restaurant. Just get the information and it all done.\n",
    "goal_dict": {
        "taxi": {},
        "police": {},
        "hospital": {},
        "attraction": {},
        "train": {},
        "message": "Task 06075: You want to find an expensive restaurant and it should be in the east part of town. You want to know the phone number and address of the venue.",
        "restaurant": {
            "info": {
                "pricerange": "expensive",
                "area": "east"
            },
            "reqt": [
                "phone",
                "address"
            ],
            "fail_info": {}
        },
        "accommodation": {}
    }
}