{
    "dial_idx": "WOZ20485.json",
    "domains": [
        "restaurant"
    ],
    "goal_text": "Task 07986: You are looking for a moderately priced restaurant and it should be in the west part of town. You want to know the address.Remember. You don't want booking for restaurant. Just get the information and it all done.\n",
    "goal_dict": {
        "taxi": {},
        "police": {},
        "hospital": {},
        "attraction": {},
        "train": {},
        "message": "Task 07986: You are looking for a moderately priced restaurant and it should be in the west part of town. You want to know the address.",
        "restaurant": {
            "info": {
                "pricerange": "moderate",
                "area": "west"
            },
            "reqt": [
                "address"
            ],
            "fail_info": {}
        },
        "accommodation": {}
    }
}