{
    "dial_idx": "WOZ20017.json",
    "domains": [
        "restaurant"
    ],
    "goal_text": "Task 02643: You want to find a restaurant in the centre and it should serve spanish food. You want to know the phone number and postcode of the venue.Remember. You don't want booking for restaurant. Just get the information and it all done.\n",
    "goal_dict": {
        "taxi": {},
        "police": {},
        "hospital": {},
        "attraction": {},
        "train": {},
        "message": "Task 02643: You want to find a restaurant in the centre and it should serve spanish food. You want to know the phone number and postcode of the venue.",
        "restaurant": {
            "info": {
                "food": "spanish",
                "area": "centre"
            },
            "reqt": [
                "phone",
                "postcode"
            ],
            "fail_info": {}
        },
        "accommodation": {}
    }
}