[
    {
        "call_log": "{'api_name':'show_app_description','input_parameters':{}}"
    },
    {
        "call_log": "{'api_name':'show_api_description','input_parameters':{'app_name':'accommodation'}}"
    },
    {
        "call_log": "{'api_name':'accommodation_retrieve','input_parameters':{'location':'Cambridge east','amenities':['free WiFi','free parking'],'guests':1,'check_in':'2024-06-04','check_out':'2024-06-08'}}"
    },
    {
        "call_log": "{'api_name':'show_api_docs','input_parameters':{'app_name':'accommodation','api_name':'accommodation_retrieve'}}"
    },
    {
        "call_log": "{'api_name':'accommodation_retrieve','input_parameters':{'area':'east','internet':True,'parking':True}}"
    },
    {
        "call_log": "{'api_name':'accommodation_book','input_parameters':{'id':'16','guests':1,'check_in':'2024-06-04','check_out':'2024-06-08'}}"
    },
    {
        "call_log": "{'api_name':'show_api_docs','input_parameters':{'app_name':'accommodation','api_name':'accommodation_book'}}"
    },
    {
        "call_log": "{'api_name':'accommodation_book','input_parameters':{'id':16,'day':'tuesday','stay':4,'people':1}}"
    },
    {
        "call_log": "{'api_name':'show_api_description','input_parameters':{'app_name':'train'}}"
    },
    {
        "call_log": "{'api_name':'train_retrieve','input_parameters':{'from':'Cambridge','to':'Ely','day':'tuesday','arrive_by':'21:15'}}"
    },
    {
        "call_log": "{'api_name':'show_api_docs','input_parameters':{'app_name':'train','api_name':'train_retrieve'}}"
    },
    {
        "call_log": "{'api_name':'train_retrieve','input_parameters':{'departure':'cambridge','destination':'ely','day':'tuesday'}}"
    },
    {
        "call_log": "{'api_name':'train_book','input_parameters':{'train_schedule_id':'1360','people':1}}"
    },
    {
        "call_log": "{'api_name':'train_book','input_parameters':{'train_schedule_id':1360,'people':1}}"
    }
]