[
    {
        "call_log": "{'api_name':'show_app_description','input_parameters':{}}"
    },
    {
        "call_log": "{'api_name':'show_api_description','input_parameters':{'app_name':'restaurant'}}"
    },
    {
        "call_log": "{'api_name':'restaurant_retrieve','input_parameters':{'location':'north Cambridge','cuisine':'French'}}"
    },
    {
        "call_log": "{'api_name':'show_api_docs','input_parameters':{'app_name':'restaurant','api_name':'restaurant_retrieve'}}"
    },
    {
        "call_log": "{'api_name':'restaurant_retrieve','input_parameters':{'area':'north','food':'french'}}"
    },
    {
        "call_log": "{'api_name':'show_api_docs','input_parameters':{'app_name':'restaurant','api_name':'restaurant_book'}}"
    },
    {
        "call_log": "{'api_name':'restaurant_book','input_parameters':{'id':19264,'day':'sunday','people':6,'time':'16:00'}}"
    },
    {
        "call_log": "{'api_name':'show_api_description','input_parameters':{'app_name':'accommodation'}}"
    },
    {
        "call_log": "{'api_name':'show_api_docs','input_parameters':{'app_name':'accommodation','api_name':'accommodation_retrieve'}}"
    },
    {
        "call_log": "{'api_name':'accommodation_retrieve','input_parameters':{'stars':3,'type':'guesthouse','area':'north'}}"
    },
    {
        "call_log": "{'api_name':'accommodation_book','input_parameters':{'id':4,'checkin':'sunday','nights':3,'guests':6}}"
    },
    {
        "call_log": "{'api_name':'show_api_docs','input_parameters':{'app_name':'accommodation','api_name':'accommodation_book'}}"
    },
    {
        "call_log": "{'api_name':'accommodation_book','input_parameters':{'id':4,'day':'sunday','stay':3,'people':6}}"
    },
    {
        "call_log": "{'api_name':'show_api_description','input_parameters':{'app_name':'taxi'}}"
    },
    {
        "call_log": "{'api_name':'show_api_docs','input_parameters':{'app_name':'taxi','api_name':'taxi_book'}}"
    },
    {
        "call_log": "{'api_name':'taxi_book','input_parameters':{'departure':'alpha-milton guest house','destination':'restaurant two two','arriveBy':'16:00'}}"
    }
]